backup/compile.py
backup/new_template.py
backup/ERP/__init__.py
backup/ERP/inventory_overview.py
backup/ERP/replace_logic.py
backup/ERP/ERP_PACKAGE/__init__.py
backup/ERP/ERP_PACKAGE/erp_master_data_inquiries.py
backup/ERP/ERP_PACKAGE/handle_changes_on_purchase_order_from_suppliers.py
backup/ERP/broken_down/create_purchase_order.py
backup/ERP/broken_down/get_inventory_projection.py
backup/ERP/real_broken_down/confirm_delivery_date.py
backup/ERP/real_broken_down/create_purchase_order.py
backup/ERP/real_broken_down/modify_purchase_order.py
backup/SLR/Knowledge Management.py
backup/SLR/List Inventory Projections Results.py
backup/SLR/Maintain Fixed Order Quantities Materials.py
backup/SLR/View Material Inventory Projection.py
backup/SLR/list_material_planning_results.py
backup/SLR/material_planning.py
backup/SLR/order placement sd.py
backup/SLR/view_material_planning_result.py
backup/archive/azure_queue_handler_tool.py
backup/archive/demo_todo_app.py
backup/archive/full_test.py
backup/archive/human_in_the_loop_node_interrupt.py
backup/archive/human_in_the_loop_test.py
backup/archive/send_an_email.py
backup/archive/shit_python_pst.py
backup/archive/supervisor_o1.py
backup/archive/test-code.py
backup/archive/test_voice.py
backup/important/expedite supply shortage.py
backup/important/knowledge_management.py
backup/important/send_a_teams_message.py
backup/important/send_a_teams_message_approval.py
recall_space_agents/__init__.py
recall_space_agents/hierarchical_agents/__init__.py
recall_space_agents/hierarchical_agents/application_graph.py
recall_space_agents/hierarchical_agents/supervisor.py
recall_space_agents/hierarchical_agents/worker.py
recall_space_agents/hierarchical_agents/realized_workers/__init__.py
recall_space_agents/hierarchical_agents/realized_workers/ai_search_manager.py
recall_space_agents/hierarchical_agents/realized_workers/azure_blob_manager.py
recall_space_agents/hierarchical_agents/realized_workers/bot_manager.py
recall_space_agents-5.0.0.dist-info/METADATA
recall_space_agents-5.0.0.dist-info/WHEEL
recall_space_agents-5.0.0.dist-info/top_level.txt
recall_space_agents-5.0.0.dist-info/RECORD
